test_report/__init__.py
test_report/controllers.py
test_report/models.py
test_report/views.py
test_report_generator-0.1.5.dist-info/LICENSE
test_report_generator-0.1.5.dist-info/METADATA
test_report_generator-0.1.5.dist-info/WHEEL
test_report_generator-0.1.5.dist-info/top_level.txt
test_report_generator-0.1.5.dist-info/RECORD
