Metadata-Version: 2.1
Name: test_report_generator
Version: 0.1.5
Summary: This is a library for generating a report for your automated tests.
Author-email: Marlon Junior <marlonrfjunior@gmail.com>
Project-URL: Homepage, https://github.com/marlonrfjunior/test_report
Project-URL: Issues, https://github.com/marlonrfjunior/test_report/issues
Classifier: Programming Language :: Python :: 3
Classifier: License :: OSI Approved :: MIT License
Classifier: Operating System :: OS Independent
Requires-Python: >=3.8
License-File: LICENSE
